{"nodes": [{"id": "pages_writeups_slug_page", "label": "Writeup Detail Page ([...slug].astro)", "file_type": "code", "source_file": "src/pages/writeups/[...slug].astro", "source_location": null, "source_url": null, "captured_at": null, "author": null, "contributor": null}, {"id": "concept_series_context", "label": "SeriesContext Navigation State", "file_type": "concept", "source_file": "src/pages/writeups/[...slug].astro", "source_location": null, "source_url": null, "captured_at": null, "author": null, "contributor": null}], "edges": [{"source": "pages_writeups_slug_page", "target": "concept_series_context", "relation": "implements", "confidence": "EXTRACTED", "confidence_score": 1.0, "source_file": "src/pages/writeups/[...slug].astro", "source_location": "L10-18", "weight": 1.0}, {"source": "pages_writeups_slug_page", "target": "concept_static_paths_pattern", "relation": "implements", "confidence": "EXTRACTED", "confidence_score": 1.0, "source_file": "src/pages/writeups/[...slug].astro", "source_location": "L22", "weight": 1.0}, {"source": "pages_writeups_slug_page", "target": "pages_writeups_index_page", "relation": "references", "confidence": "EXTRACTED", "confidence_score": 1.0, "source_file": "src/pages/writeups/[...slug].astro", "source_location": "L89", "weight": 1.0}, {"source": "concept_series_context", "target": "concept_static_paths_pattern", "relation": "conceptually_related_to", "confidence": "INFERRED", "confidence_score": 0.85, "source_file": "src/pages/writeups/[...slug].astro", "source_location": null, "weight": 0.8}, {"source": "pages_writeups_slug_page", "target": "pages_writeups_category_page", "relation": "references", "confidence": "EXTRACTED", "confidence_score": 1.0, "source_file": "src/pages/writeups/[...slug].astro", "source_location": "L99", "weight": 1.0}], "hyperedges": [{"id": "detail_pages_series_navigation", "label": "Detail Pages Sharing Series Navigation Pattern", "nodes": ["pages_writeups_slug_page", "pages_projects_slug_page", "concept_series_context"], "relation": "implement", "confidence": "EXTRACTED", "confidence_score": 0.95, "source_file": "src/pages/writeups/[...slug].astro"}]}